{
  "incomeStabilityScore" : 0.5,
  "debtToIncomeRatio" : 10.476190476190476,
  "paymentDisciplineRatio" : 1.0,
  "latePaymentSeverity" : 0.0,
  "ageIncomeRatio" : 840.0,
  "creditExperienceRatio" : 0.28,
  "avgDebtPerCount" : 24444.444444444445,
  "onTimeAmountRatio" : 1.0,
  "lateDebtFrequency" : 0.0,
  "monthlyPaymentCapacity" : 269.2307692307692,
  "loanDurationExperience" : 11.142857142857142,
  "collateralToIncome" : 6.895411904761905,
  "collateralPerMonth" : 1856.4570512820512,
  "creditUtilizationRatio" : 0.0,
  "personTc" : 10000000030,
  "loanId" : 973,
  "age" : 25,
  "monthlyIncome" : 21000.0,
  "employmentStatusCode" : 6,
  "educationLevelCode" : 3,
  "maritalStatusCode" : 1,
  "loanTypeCode" : 1,
  "loanTerm" : 78,
  "totalDebtCount" : 9,
  "totalDebtAmount" : 220000.0,
  "onTimeDebtCount" : 9,
  "onTimeDebtAmount" : 220000.0,
  "lateDebtCount" : 0,
  "lateDebtAmount" : 0.0,
  "loanApplicationsLastYear" : 5,
  "creditCardLimit" : 28000.0,
  "currentCardDebt" : 0.0,
  "creditCardUsageDuration" : 7,
  "collateralCount" : 2,
  "totalCollateralValue" : 144803.65,
  "creditScore" : 0,
  "eligibleLoanAmount" : 0
}