{
  "incomeStabilityScore" : 0.7,
  "debtToIncomeRatio" : 0.9090909090909091,
  "paymentDisciplineRatio" : 0.75,
  "latePaymentSeverity" : 0.25,
  "ageIncomeRatio" : 758.6206896551724,
  "creditExperienceRatio" : 0.10344827586206896,
  "avgDebtPerCount" : 5000.0,
  "onTimeAmountRatio" : 0.75,
  "lateDebtFrequency" : 0.25,
  "monthlyPaymentCapacity" : 244.44444444444446,
  "loanDurationExperience" : 30.0,
  "collateralToIncome" : 4.090909090909091,
  "collateralPerMonth" : 1000.0,
  "creditUtilizationRatio" : 0.4375,
  "personTc" : 10000000031,
  "loanId" : 1033,
  "age" : 29,
  "monthlyIncome" : 22000.0,
  "employmentStatusCode" : 2,
  "educationLevelCode" : 3,
  "maritalStatusCode" : 1,
  "loanTypeCode" : 1,
  "loanTerm" : 90,
  "totalDebtCount" : 4,
  "totalDebtAmount" : 20000.0,
  "onTimeDebtCount" : 3,
  "onTimeDebtAmount" : 15000.0,
  "lateDebtCount" : 1,
  "lateDebtAmount" : 5000.0,
  "loanApplicationsLastYear" : 2,
  "creditCardLimit" : 8000.0,
  "currentCardDebt" : 3500.0,
  "creditCardUsageDuration" : 3,
  "collateralCount" : 1,
  "totalCollateralValue" : 90000.0,
  "creditScore" : 0,
  "eligibleLoanAmount" : 0
}